LICENSE
MANIFEST.in
README.rst
setup.py
pybrowscap/__init__.py
pybrowscap.egg-info/PKG-INFO
pybrowscap.egg-info/SOURCES.txt
pybrowscap.egg-info/dependency_links.txt
pybrowscap.egg-info/top_level.txt
pybrowscap/loader/__init__.py
pybrowscap/loader/csv/__init__.py
pybrowscap/test/__init__.py
pybrowscap/test/data/browscap_14_05_2012.csv
pybrowscap/test/data/browscap_21_05_2012.csv
pybrowscap/test/loader/__init__.py
pybrowscap/test/loader/test_downloader.py
pybrowscap/test/loader/csv/__init__.py
pybrowscap/test/loader/csv/test_browser.py
pybrowscap/test/loader/csv/test_loader.py