Metadata-Version: 1.1
Name: pybrowscap
Version: 2.0
Summary: detects browsers capabilities and features like css, java, javascript etc.
Home-page: http://www.codescale.net/en/community#pybrowscap
Author: Vladimír Gorej
Author-email: gorej@codescale.net
License: BSD
Download-URL: http://github.com/char0n/pybrowscap/tarball/master
Keywords: browser browscap detection user agent
Platform: any
Classifier: Development Status :: 4 - Beta
Classifier: Environment :: Console
Classifier: Environment :: Web Environment
Classifier: Intended Audience :: Developers
Classifier: Intended Audience :: System Administrators
Classifier: Intended Audience :: Information Technology
Classifier: License :: OSI Approved :: BSD License
Classifier: Operating System :: OS Independent
Classifier: Programming Language :: Python
Classifier: Topic :: Utilities
Classifier: Topic :: Internet :: WWW/HTTP
Classifier: Topic :: Internet :: WWW/HTTP :: Browsers
